hw/hw6/hw6_1/control.v
/*
   CS/ECE 552, Spring '19
   Homework #6, Problem #1

   This module determines all of the control logic for the processor.
*/
module control (/*AUTOARG*/
                // Outputs
                err,
                RegDst,
                SESel,
                RegWrite,
                DMemWrite,
                DMemEn,
                ALUSrc2,
                PCSrc,
                PCImm,
                MemToReg,
                DMemDump,
                Jump,
                // Inputs
                OpCode,
                Funct
                );

   // inputs
   input [4:0]  OpCode;
   input [1:0]  Funct;

   // outputs
   output       err;
   output       RegWrite, DMemWrite, DMemEn, ALUSrc2, PCSrc,
                PCImm, MemToReg, DMemDump, Jump;
   output [1:0] RegDst;
   output [2:0] SESel;

   //TODO: Handle Error
   wire is7_5, is10_8, is_R7, zext5bit, zext8bit, ext5bit, ext8bit, zext11bit, is10010, alu_op;

   assign is_10010 = (OpCode[4:0] == 5'b10010);
   // Assign 1 if there is a jump
   assign Jump = (OpCode[4:0] == 5'b00101) | (OpCode[4:0] == 5'b00111);

   assign PCImm = (OpCode[4:0] == 5'b00100) | (OpCode[4:0] == 5'b00110);

   // Assign 1 if writing to memory
   assign DMemWrite = (OpCode[4:0] == 5'b10011) | (OpCode[4:0] == 5'b10000);

   // Assign 1 if want to dump memory - only used in halt
   assign DMemDump = (OpCode[4:0] == 5'b00000);

   // Assign 1 if loading memory into a reg
   assign MemToReg = (OpCode[4:0] == 5'b10001);

   // Assign 1 if memory is used, ie if either MemToReg or DMemDump is needed
   assign DMemEn = (MemToReg | DMemWrite);

   // Assign 1 if PC change provided by Branch/Jump (if index 4 is 0 and index 2 is 1)
   assign PCSrc = (~OpCode[4] & OpCode[2]);

   // Assign 1 if ALU uses 2 registers as operands and 0 if an immediate is used
   assign ALUSrc2 = (OpCode[4:3] == 2'b11) & (|OpCode[2:1]);

   // Assign 1 if a reg is being written to and 0 elsewise
   assign RegWrite = (OpCode[4] & |OpCode[3:0]) | (OpCode[4:1] == 4'b0011) | (OpCode[4:2] == 3'b010);

   // Assign 1 if instruction specifies dest reg is in bits 7:5
   assign is7_5 = (OpCode[4:2] == 3'b010) | ((OpCode[4:3] == 2'b10) & (~OpCode[4:1] == 4'b1001));

   assign is10_8 = (OpCode[4:0] == 5'b11000) | (OpCode[4:1] == 4'b1001);

   assign is_R7 = (OpCode[4:1] == 4'b0011);

   // Assign 00 if bits 4:2 specify destination (same as ALUSrc2)
   assign RegDst = (ALUSrc2) ? 2'b00
                     // Assign 01 if bits 7:5 specify destination
                     : (is7_5) ? 2'b01
                     // Assign 10 if bits 10:8 specify destination
                     : (is10_8) ? 2'b10
                     // Otherwise assign 11 if JAL or JALR
                     : (is_R7) ? 2'b11
                     // Otherwise dont care
                     : 2'bxx;

   // Set immediate extension recognition bits
   assign zext5bit = (OpCode[4:2] == 3'b101) | (OpCode[4:1] == 4'b0101);
   assign ext5bit = (OpCode[4:1] == 4'b0100) | ((OpCode[4:2] == 3'b100) & (~is_10010));
   assign zext8bit = is_10010;
   assign ext8bit = (OpCode[4:2] == 3'b011) | (OpCode[4:0] == 5'b11000) | (OpCode[4:0] == 5'b00101) | (OpCode[4:0] == 5'b00111);
   assign zext11bit = (OpCode[4:0] == 5'b00100) | (OpCode[4:0] == 5'b00110);

   assign SESel = (zext5bit) ? 3'b000
                     : (ext5bit) ? 3'b01x
                     : (zext8bit) ? 3'b001
                     : (ext8bit) ? 3'b10x
                     : (zext11bit) ? 3'b11x
                     : 3'bxxx;

   // Check for any unknown vals
   assign err = (^OpCode === 1'bx) | // if any bits of opcode are unkown
                ((OpCode[4:1] === 4'b1101) & (^Funct === 1'bx)); // or if it's a function reliant opcode, and func bits unkown
endmodule

hw/hw6/hw6_1/clkrst.v
/* $Author: karu $ */
/* $LastChangedDate: 2009-03-04 23:09:45 -0600 (Wed, 04 Mar 2009) $ */
/* $Rev: 45 $ */
// clock and reset generator
// CS/ECE 552
// Andy Phelps (TA)
// 3/22/06

// Clock period is 100 time units, and reset length
// to 201 time units (two rising edges of clock).

module clkrst (clk, rst, err);

    output clk;
    output rst;
    input  err;

    reg clk;
    reg rst;
    integer cycle_count;

    initial begin
      $dumpvars;
      cycle_count = 0;
      rst = 1;
      clk = 1;
      #201 rst = 0; // delay until slightly after two clock periods
    end

    always #50 begin   // delay 1/2 clock period each time thru loop
      clk = ~clk;
      if (clk & err) begin
        $display("Error signal asserted");
        $stop;
      end
    end

    always @(posedge clk) begin
       cycle_count = cycle_count + 1;
       if (cycle_count > 100000) begin
          $display("hmm....more than 100000 cycles of simulation...error?\n");
          $finish;
       end
    end


endmodule
// DUMMY LINE FOR REV CONTROL :0:

hw/hw6/hw6_1/control_hier.v
/*
   CS/ECE 552, Spring '19
   Homework #6, Problem #1

   Wrapper module around global control logic.
   YOU SHALL NOT EDIT THIS FILE. ANY CHANGES TO THIS FILE WILL
   RESULT IN ZERO FOR THIS PROBLEM.
*/
module control_hier (/*AUTOARG*/
                     // Outputs
                     err,
                     RegDst,
                     SESel,
                     RegWrite,
                     DMemWrite,
                     DMemEn,
                     ALUSrc2,
                     PCSrc,
                     PCImm,
                     MemToReg,
                     DMemDump,
                     Jump,
                     // Inputs
                     OpCode,
                     Funct
                     );

   // inputs
   input [4:0]  OpCode;
   input [1:0]  Funct;

   // outputs
   output       err;
   output       RegWrite, DMemWrite, DMemEn, ALUSrc2, PCSrc,
                PCImm, MemToReg, DMemDump, Jump;
   output [1:0] RegDst;
   output [2:0] SESel;

   wire         clk, rst, errClkRst;

   // Ignore errClkRst for now
   clkrst clk_generator(.clk(clk), .rst(rst), .err(errClkRst) );
   control c0(
              // Outputs
              .err                          (err),
              .RegDst                       (RegDst),
              .SESel                        (SESel),
              .RegWrite                     (RegWrite),
              .DMemWrite                    (DMemWrite),
              .DMemEn                       (DMemEn),
              .ALUSrc2                      (ALUSrc2),
              .PCSrc                        (PCSrc),
              .PCImm                        (PCImm),
              .MemToReg                     (MemToReg),
              .DMemDump                     (DMemDump),
              .Jump                         (Jump),
              // Inputs
              .OpCode                       (OpCode),
              .Funct                        (Funct));

endmodule

hw/hw6/hw6_1/control_hier_bench.v
/*
   CS/ECE 552, Spring '19
   Homework #5, Problem #1

   Random testbench for the 8x16b register file.
*/
module control_hier_bench(/*AUTOARG*/);
   /*AUTOWIRE*/
   // Beginning of automatic wires (for undeclared instantiated-module outputs)
   wire       err;
   wire       RegWrite, DMemWrite,              // From top of control_hier.v
              DMemEn, ALUSrc2, PCSrc,           // From top of control_hier.v
              PCImm, MemToReg, DMemDump, Jump;         // From top of control_hier.v
   wire [1:0] RegDst;                           // From top of control_hier.v
   wire [2:0] SESel;                            // From top of control_hier.v
   // End of automatics
   /*AUTOREGINPUT*/
   // Beginning of automatic reg inputs (for undeclared instantiated-module inputs)
   reg [4:0]  OpCode;                           // To top of control_hier.v
   reg [1:0]  Funct;                            // To top of control_hier.v
   // End of automatics

   integer    cycle_count;

   wire       clk;
   wire       rst;

   reg        fail;
   reg [5:0]  count;

   // Instantiate the module we want to verify

   control_hier DUT(/*AUTOINST*/
                    // Outputs
                    .err                          (err),
                    .RegDst                       (RegDst),
                    .SESel                        (SESel),
                    .RegWrite                     (RegWrite),
                    .DMemWrite                    (DMemWrite),
                    .DMemEn                       (DMemEn),
                    .ALUSrc2                      (ALUSrc2),
                    .PCSrc                        (PCSrc),
                    .PCImm                        (PCImm),
                    .MemToReg                     (MemToReg),
                    .DMemDump                     (DMemDump),
                    .Jump                         (Jump),
                    // Inputs
                    .OpCode                       (OpCode),
                    .Funct                        (Funct));

   assign               clk = DUT.clk_generator.clk;
   assign               rst = DUT.clk_generator.rst;

   initial begin
      OpCode = 5'b00000;
      count = 6'b000000;
   end

   // Enumerate all possible opcodes
   always @ (posedge clk)begin
      $display("At Opcode: %b   ->   Error: %b, RegDst: %b, SESel: %b, RegWrite: %b, DMemWrite: %b, DMemEn: %b, ALUSrc2: %b, PCSrc: %b, MemToReg: %b, DMemDump: %b, Jump: %b \n", OpCode, err,
                RegDst,
                SESel,
                RegWrite,
                DMemWrite,
                DMemEn,
                ALUSrc2,
                PCSrc,
                MemToReg,
                DMemDump,
                Jump);
      OpCode = OpCode + 1;
      count = count + 1;
      if (count == 6'b100000) begin
         $finish;
      end
   end
endmodule // control_hier_bench

hw/hw6/dump.vcd
$date
	Mon Mar 04 23:24:43 2019
$end
$version
	ModelSim Version 10.4a
$end
$timescale
	1ns
$end

$scope module control_hier_bench $end
$var wire 1 ! err $end
$var wire 1 " RegWrite $end
$var wire 1 # DMemWrite $end
$var wire 1 $ DMemEn $end
$var wire 1 % ALUSrc2 $end
$var wire 1 & PCSrc $end
$var wire 1 ' PCImm $end
$var wire 1 ( MemToReg $end
$var wire 1 ) DMemDump $end
$var wire 1 * Jump $end
$var wire 1 + RegDst [1] $end
$var wire 1 , RegDst [0] $end
$var wire 1 - SESel [2] $end
$var wire 1 . SESel [1] $end
$var wire 1 / SESel [0] $end
$var reg 5 0 OpCode [4:0] $end
$var reg 2 1 Funct [1:0] $end
$var integer 32 2 cycle_count $end
$var wire 1 3 clk $end
$var wire 1 4 rst $end
$var reg 1 5 fail $end
$var reg 6 6 count [5:0] $end

$scope module DUT $end
$var wire 1 7 OpCode [4] $end
$var wire 1 8 OpCode [3] $end
$var wire 1 9 OpCode [2] $end
$var wire 1 : OpCode [1] $end
$var wire 1 ; OpCode [0] $end
$var wire 1 < Funct [1] $end
$var wire 1 = Funct [0] $end
$var wire 1 ! err $end
$var wire 1 " RegWrite $end
$var wire 1 # DMemWrite $end
$var wire 1 $ DMemEn $end
$var wire 1 % ALUSrc2 $end
$var wire 1 & PCSrc $end
$var wire 1 ' PCImm $end
$var wire 1 ( MemToReg $end
$var wire 1 ) DMemDump $end
$var wire 1 * Jump $end
$var wire 1 + RegDst [1] $end
$var wire 1 , RegDst [0] $end
$var wire 1 - SESel [2] $end
$var wire 1 . SESel [1] $end
$var wire 1 / SESel [0] $end
$var wire 1 > clk $end
$var wire 1 ? rst $end
$var wire 1 @ errClkRst $end

$scope module clk_generator $end
$var reg 1 A clk $end
$var reg 1 B rst $end
$var wire 1 @ err $end
$var integer 32 C cycle_count $end
$upscope $end

$scope module c0 $end
$var wire 1 7 OpCode [4] $end
$var wire 1 8 OpCode [3] $end
$var wire 1 9 OpCode [2] $end
$var wire 1 : OpCode [1] $end
$var wire 1 ; OpCode [0] $end
$var wire 1 < Funct [1] $end
$var wire 1 = Funct [0] $end
$var wire 1 ! err $end
$var wire 1 " RegWrite $end
$var wire 1 # DMemWrite $end
$var wire 1 $ DMemEn $end
$var wire 1 % ALUSrc2 $end
$var wire 1 & PCSrc $end
$var wire 1 ' PCImm $end
$var wire 1 ( MemToReg $end
$var wire 1 ) DMemDump $end
$var wire 1 * Jump $end
$var wire 1 + RegDst [1] $end
$var wire 1 , RegDst [0] $end
$var wire 1 - SESel [2] $end
$var wire 1 . SESel [1] $end
$var wire 1 / SESel [0] $end
$var wire 1 D is7_5 $end
$var wire 1 E is10_8 $end
$var wire 1 F is_R7 $end
$var wire 1 G zext5bit $end
$var wire 1 H zext8bit $end
$var wire 1 I ext5bit $end
$var wire 1 J ext8bit $end
$var wire 1 K zext11bit $end
$var wire 1 L is10010 $end
$var wire 1 M alu_op $end
$var wire 1 N is_10010 $end
$upscope $end
$upscope $end
$upscope $end
$enddefinitions $end
#0
$dumpvars
b1 0
bx 1
x5
b1 6
1A
1B
bx 2
b1 C
0!
0"
0#
0$
0%
0&
0'
0(
0)
0*
x,
x+
x/
x.
x-
13
14
1>
1?
z@
0D
0E
0F
0G
0H
0I
0J
0K
zL
zM
0N
x=
x<
1;
0:
09
08
07
$end
#50
0A
0>
03
#100
1A
1>
13
b10 0
b10 6
b10 C
0;
1:
#150
0A
0>
03
#200
1A
1>
13
b11 0
b11 6
b11 C
1;
#201
0B
04
0?
#250
0A
0>
03
#300
1A
1>
13
b100 0
b100 6
b100 C
0;
0:
19
1K
1'
1&
1.
1-
#350
0A
0>
03
#400
1A
1>
13
b101 0
b101 6
b101 C
1;
0K
1J
0'
1*
0.
#450
0A
0>
03
#500
1A
1>
13
b110 0
b110 6
b110 C
0;
1:
1K
0J
1"
1'
0*
1F
1,
1+
1.
#550
0A
0>
03
#600
1A
1>
13
b111 0
b111 6
b111 C
1;
0K
1J
0'
1*
0.
#650
0A
0>
03
#700
1A
1>
13
b1000 0
b1000 6
b1000 C
0;
0:
09
18
0J
0*
1I
0F
1D
0&
0+
1.
0-
#750
0A
0>
03
#800
1A
1>
13
b1001 0
b1001 6
b1001 C
1;
#850
0A
0>
03
#900
1A
1>
13
b1010 0
b1010 6
b1010 C
0;
1:
0I
1G
0/
0.
#950
0A
0>
03
#1000
1A
1>
13
b1011 0
b1011 6
b1011 C
1;
#1050
0A
0>
03
#1100
1A
1>
13
b1100 0
b1100 6
b1100 C
0;
0:
19
1J
0"
0G
0D
1&
x,
x+
x/
1-
#1150
0A
0>
03
#1200
1A
1>
13
b1101 0
b1101 6
b1101 C
1;
#1250
0A
0>
03
#1300
1A
1>
13
b1110 0
b1110 6
b1110 C
0;
1:
#1350
0A
0>
03
#1400
1A
1>
13
b1111 0
b1111 6
b1111 C
1;
#1450
0A
0>
03
#1500
1A
1>
13
b10000 0
b10000 6
b10000 C
0;
0:
09
08
17
0J
1#
1I
0&
1.
0-
1$
#1550
0A
0>
03
#1600
1A
1>
13
b10001 0
b10001 6
b10001 C
1;
1"
1(
0#
#1650
0A
0>
03
#1700
1A
1>
13
b10010 0
b10010 6
b10010 C
0;
1:
1E
0(
1N
0,
1+
0$
1H
0I
1/
0.
#1750
0A
0>
03
#1800
1A
1>
13
b10011 0
b10011 6
b10011 C
1;
1#
0N
1$
0H
1I
x/
1.
#1850
0A
0>
03
#1900
1A
1>
13
b10100 0
b10100 6
